Metadata-Version: 2.1
Name: SpiderKidSDK
Version: 0.0.3
Summary: SpiderKid Software Development Kit
Home-page: https://github.com/Jyonn/SpiderKidSDK
Author: Jyonn Liu
Author-email: liu@qijiong.work
